warthog/__init__.py
warthog/pywarthog.py
pywarthog-0.1.2.dist-info/METADATA
pywarthog-0.1.2.dist-info/WHEEL
pywarthog-0.1.2.dist-info/licenses/LICENSE
pywarthog-0.1.2.dist-info/RECORD
