Metadata-Version: 2.1
Name: pywarthog
Version: 0.1.2
Summary: A Python library for the Warthog API
Project-URL: Homepage, https://github.com/zzjulien/pywarthog
Project-URL: Issues, https://github.com/zzjulien/pywarthog/issues
Author-email: zzjulien <tpypi@zzjulien.maskmy.id>
License-File: LICENSE
Classifier: License :: OSI Approved :: MIT License
Classifier: Operating System :: OS Independent
Classifier: Programming Language :: Python :: 3
Requires-Python: >=3.10
